hwlearn/Learning.py
hwlearn/Network.py
hwlearn/__init__.py
hwlean-0.0.1.dist-info/LICENSE
hwlean-0.0.1.dist-info/METADATA
hwlean-0.0.1.dist-info/WHEEL
hwlean-0.0.1.dist-info/top_level.txt
hwlean-0.0.1.dist-info/RECORD
