Metadata-Version: 2.1
Name: hwlean
Version: 0.0.1
Summary: My first Python package
Author: William Dennis
Author-email: wwdennis.home@gmail.com
Keywords: python,first package
License-File: LICENSE
Requires-Dist: hwlearn
Requires-Dist: numpy
